<?xml version="1.0"?>
<student>
  <studentId>394</studentId>
  <studentName>Kabanyana Claudia</studentName>
  <accademicHistory>
    <institution>
      <institutionName>Lyc&#xE9;e Notre Dame de Citeaux</institutionName>
      <specialization>Certificate of Secondary Education</specialization>
      <levelId>4</levelId>
      <indexNumber>3970/REB/E&amp;AD/2013</indexNumber>
      <award/>
      <grade/>
      <startYear/>
      <endYear/>
    </institution>
    <institution>
      <institutionName>Lyc&#xE9;e Notre Dame de Citeaux</institutionName>
      <specialization>MCB</specialization>
      <levelId>8</levelId>
      <indexNumber>4770/REB/E&amp;AD/2013</indexNumber>
      <award/>
      <grade/>
      <startYear/>
      <endYear/>
    </institution>
  </accademicHistory>
  <employmentHistory/>
  <financialSponsor>
    <sponsor>
      <sponsorName>Mbundi Benjamin</sponsorName>
      <payerId>11</payerId>
      <postalAddress>924 kigali</postalAddress>
      <physicalAddress>924 kigali</physicalAddress>
      <fax/>
      <sponsorfax>+250788305040</sponsorfax>
      <mobile>+250788305040</mobile>
      <email>mbundi2000@yahoo.com</email>
      <financedItem/>
      <extraInformation/>
    </sponsor>
  </financialSponsor>
  <nextOfKins>
    <nextOfKin>
      <kinName>Mbundi Benjamin</kinName>
      <relationship>Father</relationship>
      <postalAddress>924 kigali</postalAddress>
      <physicalAddress>924 kigali</physicalAddress>
      <fax/>
      <telephone>+250788305040</telephone>
      <mobile>+250788305040</mobile>
      <email>mbundi2000@yahoo.com</email>
      <extraInformation/>
    </nextOfKin>
  </nextOfKins>
  <banks/>
  <subjects/>
  <results/>
</student>
