<?xml version="1.0"?>
<student>
  <studentId>258</studentId>
  <studentName>EDGAR M MACHA</studentName>
  <accademicHistory>
    <institution>
      <institutionName>ST JOSEPH MILLENNIUM SECONDARY SCHOOL</institutionName>
      <specialization>Certificate of Secondary Education</specialization>
      <levelId>4</levelId>
      <indexNumber>S3674/0051</indexNumber>
      <award/>
      <grade/>
      <startYear/>
      <endYear/>
    </institution>
    <institution>
      <institutionName>ST JOSEPHS CATHEDRAL SECONDARY SCHOOL</institutionName>
      <specialization>PCB</specialization>
      <levelId>8</levelId>
      <indexNumber>S4692/0599</indexNumber>
      <award/>
      <grade/>
      <startYear/>
      <endYear/>
    </institution>
  </accademicHistory>
  <employmentHistory/>
  <financialSponsor>
    <sponsor>
      <sponsorName>HESLB</sponsorName>
      <payerId>11</payerId>
      <postalAddress>BOX 76068 DAR ES SALAAM</postalAddress>
      <physicalAddress>Sam Nujoma Road, Mwenge</physicalAddress>
      <fax/>
      <sponsorfax>+255222772432</sponsorfax>
      <mobile>+255222772432</mobile>
      <email>info@heslb.go.tz</email>
      <financedItem/>
      <extraInformation/>
    </sponsor>
  </financialSponsor>
  <nextOfKins>
    <nextOfKin>
      <kinName>DOREEN MANSUETUS MACHA</kinName>
      <relationship>MOTHER</relationship>
      <postalAddress>BOX 39836 DAR ES SALAAM</postalAddress>
      <physicalAddress>TABATA SEGEREA</physicalAddress>
      <fax/>
      <telephone>0754658898</telephone>
      <mobile>0754658898</mobile>
      <email>salaamedgar@yahoo.com</email>
      <extraInformation/>
    </nextOfKin>
  </nextOfKins>
  <banks/>
  <subjects/>
  <results/>
</student>
