<?xml version="1.0"?>
<student>
  <studentId>86</studentId>
  <studentName>ESCOR NASSON TWEVE</studentName>
  <accademicHistory>
    <institution>
      <institutionName>TAMBAZA SECONDARY SCHOOL</institutionName>
      <specialization>Certificate of Secondary Education</specialization>
      <levelId>4</levelId>
      <indexNumber>S0347-060</indexNumber>
      <award/>
      <grade/>
      <startYear/>
      <endYear/>
    </institution>
    <institution>
      <institutionName>MOSHI SECONDARY SCHOOL</institutionName>
      <specialization>PCB</specialization>
      <levelId>8</levelId>
      <indexNumber>S0134-517</indexNumber>
      <award/>
      <grade/>
      <startYear/>
      <endYear/>
    </institution>
    <institution>
      <institutionName>UNIVERSITY OF DAR ES SALAAM</institutionName>
      <specialization>DOCTOR OF DENTAL SURGERY(DDS)</specialization>
      <levelId>15</levelId>
      <indexNumber>13337/T92</indexNumber>
      <award/>
      <grade/>
      <startYear/>
      <endYear/>
    </institution>
  </accademicHistory>
  <employmentHistory>
    <employer>
      <employerName>MINISTRY OF HEALTH AND SOCIAL WELFARE</employerName>
      <postalAddress>box 9083 DAR ES SALAAM</postalAddress>
      <physicalAddress>MINISTRY OF HEALTH ,SAMORA AV. </physicalAddress>
      <telephone>00255262394570</telephone>
      <email>pm@moh.go.tz</email>
      <mobile/>
      <fax/>
      <startYear/>
      <endYear/>
      <extraInformation/>
    </employer>
  </employmentHistory>
  <financialSponsor>
    <sponsor>
      <sponsorName>MINISTRY OF HEALTH &amp; SOCIAL WELFARE</sponsorName>
      <payerId>11</payerId>
      <postalAddress>BOX 9083 DAR ES SALAAM</postalAddress>
      <physicalAddress>MOHSW HQ SAMORA AV.</physicalAddress>
      <fax/>
      <sponsorfax>00255222113077</sponsorfax>
      <mobile>00255787646464</mobile>
      <email>pm@moh.go.tz</email>
      <financedItem/>
      <extraInformation/>
    </sponsor>
  </financialSponsor>
  <nextOfKins>
    <nextOfKin>
      <kinName>MRS VERONICA TWEVE</kinName>
      <relationship>WIFE</relationship>
      <postalAddress>BOX 1489 DODOMA</postalAddress>
      <physicalAddress>MIREMBE HOSPITAL COMPOUND</physicalAddress>
      <fax/>
      <telephone>00255755863666</telephone>
      <mobile>00255755863666</mobile>
      <email>neemaet1992@gmail.com</email>
      <extraInformation/>
    </nextOfKin>
  </nextOfKins>
  <banks/>
  <subjects/>
  <results/>
</student>
