<?xml version="1.0"?>
<student>
  <studentId>389</studentId>
  <studentName>monica vincent </studentName>
  <accademicHistory>
    <institution>
      <institutionName>visitation girls secondary school</institutionName>
      <specialization>Certificate of Secondary Education</specialization>
      <levelId>4</levelId>
      <indexNumber>S0263.0033.2003</indexNumber>
      <award/>
      <grade/>
      <startYear/>
      <endYear/>
    </institution>
    <institution>
      <institutionName>st.mary goreti secondary school</institutionName>
      <specialization>PCB</specialization>
      <levelId>8</levelId>
      <indexNumber>P0134.0554.2007</indexNumber>
      <award/>
      <grade/>
      <startYear/>
      <endYear/>
    </institution>
  </accademicHistory>
  <employmentHistory>
    <employer>
      <employerName>ras kilimanjaro</employerName>
      <postalAddress>p o box 3070</postalAddress>
      <physicalAddress>katibu tawala mkoa</physicalAddress>
      <telephone>+255272752321</telephone>
      <email>raskilimanjaro@yahoo.co.uk</email>
      <mobile/>
      <fax/>
      <startYear/>
      <endYear/>
      <extraInformation/>
    </employer>
  </employmentHistory>
  <financialSponsor>
    <sponsor>
      <sponsorName>higher education student loans board</sponsorName>
      <payerId>11</payerId>
      <postalAddress>76068</postalAddress>
      <physicalAddress>msasani dar-es salam</physicalAddress>
      <fax/>
      <sponsorfax>+255222772432</sponsorfax>
      <mobile>0786227539</mobile>
      <email>info@heslb.go.tz</email>
      <financedItem/>
      <extraInformation/>
    </sponsor>
  </financialSponsor>
  <nextOfKins>
    <nextOfKin>
      <kinName>elsa estomick kuringe</kinName>
      <relationship>daughter</relationship>
      <postalAddress>8901</postalAddress>
      <physicalAddress>kilimanjaro</physicalAddress>
      <fax/>
      <telephone>0754323989</telephone>
      <mobile>0754323989</mobile>
      <email>kuringeo@gmail.com</email>
      <extraInformation/>
    </nextOfKin>
  </nextOfKins>
  <banks><bank><accountName>VINCENT, MONICA</accountName><bankAccount>0112040387500</bankAccount><bankName> CRDB </bankName><branchName></branchName></bank></banks>
  <subjects/>
  <results/>
<isaacompletechecksum>e9c73f4ca58effc14d3b741dd7ac61b2</isaacompletechecksum></student>
