<?xml version="1.0"?>
<student>
  <studentId>3338</studentId>
  <studentName>Francis Alfred Masse</studentName>
  <accademicHistory>
    <institution>
      <institutionName>Don Bosco Seminary</institutionName>
      <specialization>Certificate of Secondary Education</specialization>
      <levelId>4</levelId>
      <indexNumber>0010</indexNumber>
      <award/>
      <grade/>
      <startYear/>
      <endYear/>
    </institution>
    <institution>
      <institutionName>Mzumbe High School</institutionName>
      <specialization>PCB</specialization>
      <levelId>8</levelId>
      <indexNumber>00540</indexNumber>
      <award/>
      <grade/>
      <startYear/>
      <endYear/>
    </institution>
    <institution>
      <institutionName>Muhimbili University</institutionName>
      <specialization>DOCTOR OF MEDICINE</specialization>
      <levelId>15</levelId>
      <indexNumber>2006-04-01325</indexNumber>
      <award/>
      <grade/>
      <startYear/>
      <endYear/>
    </institution>
  </accademicHistory>
  <employmentHistory>
    <employer>
      <employerName>Tanzania Peoples Defense Forces</employerName>
      <postalAddress>9203</postalAddress>
      <physicalAddress>DAR ES SALAAM</physicalAddress>
      <telephone>+255222150556</telephone>
      <email>signalcenter@cats-net.com</email>
      <mobile/>
      <fax/>
      <startYear/>
      <endYear/>
      <extraInformation/>
    </employer>
  </employmentHistory>
  <financialSponsor>
    <sponsor>
      <sponsorName>Tanzania Peoples Defense Force</sponsorName>
      <payerId>11</payerId>
      <postalAddress>9203</postalAddress>
      <physicalAddress>DAR ES SALAAM</physicalAddress>
      <fax/>
      <sponsorfax>+255222150556</sponsorfax>
      <mobile>0717796381</mobile>
      <email>signalcenter@cats-net.com</email>
      <financedItem/>
      <extraInformation/>
    </sponsor>
  </financialSponsor>
  <nextOfKins>
    <nextOfKin>
      <kinName>Alfred Mokiri Masse</kinName>
      <relationship>Father</relationship>
      <postalAddress>9203</postalAddress>
      <physicalAddress>Morogoro</physicalAddress>
      <fax/>
      <telephone>+255222150556</telephone>
      <mobile>0754642448</mobile>
      <email>alfredmasse@yahoo.com</email>
      <extraInformation/>
    </nextOfKin>
  </nextOfKins>
  <banks/>
  <subjects/>
  <results/>
</student>
