<?xml version="1.0"?>
<student>
  <studentId>958</studentId>
  <studentName>FABIAN MJIE</studentName>
  <accademicHistory>
    <institution>
      <institutionName>MWENGE SECONDARY SCHOOL</institutionName>
      <specialization>Certificate of Secondary Education</specialization>
      <levelId>4</levelId>
      <indexNumber>S0334-087</indexNumber>
      <award/>
      <grade/>
      <startYear/>
      <endYear/>
    </institution>
    <institution>
      <institutionName>MOSHI SECONDARY SCHOOL</institutionName>
      <specialization>PCM</specialization>
      <levelId>8</levelId>
      <indexNumber>S0134-0602</indexNumber>
      <award/>
      <grade/>
      <startYear/>
      <endYear/>
    </institution>
  </accademicHistory>
  <employmentHistory/>
  <financialSponsor>
    <sponsor>
      <sponsorName>SEBASTIAN MJIE</sponsorName>
      <payerId>11</payerId>
      <postalAddress>575 SINGIDA</postalAddress>
      <physicalAddress>SINGIDA</physicalAddress>
      <fax/>
      <sponsorfax>0769892563</sponsorfax>
      <mobile>0769892563</mobile>
      <email>fabiamjie@yahoo.com</email>
      <financedItem/>
      <extraInformation/>
    </sponsor>
  </financialSponsor>
  <nextOfKins>
    <nextOfKin>
      <kinName>Marcel Mjie</kinName>
      <relationship>Father</relationship>
      <postalAddress>575 SINGIDA</postalAddress>
      <physicalAddress>SINGIDA</physicalAddress>
      <fax/>
      <telephone>0768645575</telephone>
      <mobile>0768645575</mobile>
      <email>fabianmjie@yahoo.com</email>
      <extraInformation/>
    </nextOfKin>
  </nextOfKins>
  <banks/>
  <subjects/>
  <results/>
</student>
