<?xml version="1.0"?>
<student>
  <studentId>3175</studentId>
  <studentName>SALEHE YASINI MMBAGA</studentName>
  <accademicHistory>
    <institution>
      <institutionName>KIBACHA SECONDARY SCHOOL</institutionName>
      <specialization>Certificate of Secondary Education</specialization>
      <levelId>4</levelId>
      <indexNumber>S1422.0198.2012</indexNumber>
      <award/>
      <grade/>
      <startYear/>
      <endYear/>
    </institution>
    <institution>
      <institutionName>KIGONSERA SECONDARY SCHOOL</institutionName>
      <specialization>PCB</specialization>
      <levelId>8</levelId>
      <indexNumber>S0120.0747.2015</indexNumber>
      <award/>
      <grade/>
      <startYear/>
      <endYear/>
    </institution>
  </accademicHistory>
  <employmentHistory/>
  <financialSponsor>
    <sponsor>
      <sponsorName>HIGHER EDUCATION STUDENTS LOAN BOARD</sponsorName>
      <payerId>11</payerId>
      <postalAddress>PO BOX 76068 DSM</postalAddress>
      <physicalAddress>PO BOX 76068 DSM</physicalAddress>
      <fax/>
      <sponsorfax>+255222772432</sponsorfax>
      <mobile>+255222772432</mobile>
      <email>info@heslb.go.tz</email>
      <financedItem/>
      <extraInformation/>
    </sponsor>
  </financialSponsor>
  <nextOfKins>
    <nextOfKin>
      <kinName>YASINI MMBAGA</kinName>
      <relationship>FATHER</relationship>
      <postalAddress>PO BOX 17 SAME</postalAddress>
      <physicalAddress>0787696912</physicalAddress>
      <fax/>
      <telephone>0787696912</telephone>
      <mobile>0787696912</mobile>
      <email>salehemmbaga5@gmail.com</email>
      <extraInformation/>
    </nextOfKin>
  </nextOfKins>
  <banks><bank><accountName>MMBAGA, SALEHE YASINI</accountName><bankAccount>0152327985900</bankAccount><bankName>CRDB</bankName><branchName></branchName></bank></banks>
  <subjects/>
  <results/>
<isaacompletechecksum>9db0a6ac64c49419e9ead7248de3a7b7</isaacompletechecksum></student>
