<?xml version="1.0"?>
<student>
  <studentId>4758</studentId>
  <studentName>TUMAINIEL JACKSON KOWERO</studentName>
  <accademicHistory><institution><institutionName>DULUTI SECONDARY SCHOOL</institutionName><specialization>SCIENCE</specialization><levelId>4</levelId><indexNumber>S3646.0056.2013</indexNumber><award>ORDINARY LEVEL CERTIFICATE</award><grade>DIVISION ONE</grade><startYear>2010</startYear><endYear>2013</endYear></institution><institution><institutionName>BIHAWANA SECONDARY SCHOOL</institutionName><specialization>SCIENCE</specialization><levelId>8</levelId><indexNumber>S0103.0890.2016</indexNumber><award>ADVANCED LEVEL CERTIFICATE</award><grade>DIVISON THREE</grade><startYear>2014</startYear><endYear>2016</endYear></institution></accademicHistory>
  <employmentHistory/>
  <financialSponsor><sponsor><sponsorName>JACKSON KOWERO </sponsorName><payerId>3</payerId><postalAddress>P.O BOX 256 USA RIVER</postalAddress><physicalAddress>ARUSHA</physicalAddress><fax/><telephone/><mobile>0622443760</mobile><email/><financedItem>TUITION FEES,ACCOMODATION,MEALS </financedItem><extraInformation/></sponsor></financialSponsor>
  <nextOfKins><nextOfKin><kinName>JACKSON SIFUEL KOWERO</kinName><relationship>FATHER </relationship><postalAddress>P.O BOX 256 USA RIVER</postalAddress><physicalAddress>ARUSHA</physicalAddress><fax></fax><telephone>+255622443760</telephone><mobile>0757443760</mobile><email></email><extraInformation></extraInformation></nextOfKin></nextOfKins>
  <banks><bank><accountName>TUMAINIEL JACKSON KOWERO </accountName><bankAccount>52010009160</bankAccount><bankName>NMB</bankName><branchName>UDOM</branchName></bank></banks>
  <subjects/>
  <results/>
<isaacompletechecksum>ff8d5523f29db901144de9e872197460</isaacompletechecksum></student>
