<?xml version="1.0"?>
<student>
  <studentId>7762</studentId>
  <studentName>SHALU KAHEMELE</studentName>
  <accademicHistory><institution><institutionName>KILAKALA SECONDARY SCHOOL</institutionName><specialization>SCIENCE</specialization><levelId>4</levelId><indexNumber>S0206.0071.2008</indexNumber><award>CERTIFICATE OF SECONDARY EDUCATION</award><grade>DIVISION ONE</grade><startYear>2005</startYear><endYear>2008</endYear></institution></accademicHistory>
  <employmentHistory/>
  <financialSponsor><sponsor><sponsorName>VINCENT KAHEMELE</sponsorName><payerId>3</payerId><postalAddress>P.O.BOX 5159 DAR ES SALAAM</postalAddress><physicalAddress>PUGU, ILALA , DAR ES SALAAM</physicalAddress><fax/><telephone>0788827740</telephone><mobile>0789010169</mobile><email>vinlukah@gmail.com</email><financedItem>accommodation,meals and tuition fee</financedItem><extraInformation/></sponsor></financialSponsor>
  <nextOfKins><nextOfKin><kinName>VINCENT KAHEMELE</kinName><relationship>FATHER</relationship><postalAddress>P.O.BOX 5159 DAR ES SALAAM</postalAddress><physicalAddress>PUGU, ILALA , DAR ES SALAAM</physicalAddress><fax></fax><telephone>0788827740</telephone><mobile>0789010169</mobile><email>vinlukah@gmail.com</email><extraInformation></extraInformation></nextOfKin></nextOfKins>
  <banks><bank><accountName>SHALU ANSTEY KAHEMELE</accountName><bankAccount>23010020142</bankAccount><bankName>NATIONAL MICROFINANCE BANK</bankName><branchName>AIRPORT DSM</branchName></bank></banks>
  <subjects/>
  <results/>
<isaacompletechecksum>b6014eb2cb5a0306df9710dde4f0ecc4</isaacompletechecksum></student>
