<?xml version="1.0"?>
<student>
  <studentId>1484</studentId>
  <studentName>Evelyne Kilonzo</studentName>
  <accademicHistory>
    <institution>
      <institutionName>Kilakala Girls Secondary School</institutionName>
      <specialization>Certificate of Secondary Education</specialization>
      <levelId>4</levelId>
      <indexNumber>S0206/0012</indexNumber>
      <award/>
      <grade/>
      <startYear/>
      <endYear/>
    </institution>
    <institution>
      <institutionName>Kilakala Girls Secondary School</institutionName>
      <specialization>PCB</specialization>
      <levelId>8</levelId>
      <indexNumber>S0206/0528</indexNumber>
      <award/>
      <grade/>
      <startYear/>
      <endYear/>
    </institution>
  </accademicHistory>
  <employmentHistory/>
  <financialSponsor>
    <sponsor>
      <sponsorName>HESLB</sponsorName>
      <payerId>11</payerId>
      <postalAddress>76068</postalAddress>
      <physicalAddress>Dar es salaam</physicalAddress>
      <fax/>
      <sponsorfax>002552669036</sponsorfax>
      <mobile>00255266938</mobile>
      <email>info@heslb.go.tz</email>
      <financedItem/>
      <extraInformation/>
    </sponsor>
  </financialSponsor>
  <nextOfKins>
    <nextOfKin>
      <kinName>ELIZABETH SENGOKA KILONZO</kinName>
      <relationship>MOTHER</relationship>
      <postalAddress>P.O.BOX 254</postalAddress>
      <physicalAddress>TANGA</physicalAddress>
      <fax/>
      <telephone>00255222669072</telephone>
      <mobile>0714344934</mobile>
      <email>eliza.sengoka@yahoo.com</email>
      <extraInformation/>
    </nextOfKin>
  </nextOfKins>
  <banks/>
  <subjects/>
  <results/>
</student>
