<?xml version="1.0"?>
<student>
  <studentId>760</studentId>
  <studentName>scholastica charles</studentName>
  <accademicHistory>
    <institution>
      <institutionName>morogoro sec school</institutionName>
      <specialization>Certificate of Secondary Education</specialization>
      <levelId>4</levelId>
      <indexNumber>S0332.0069.1988</indexNumber>
      <award/>
      <grade/>
      <startYear/>
      <endYear/>
    </institution>
    <institution>
      <institutionName>kcmc school of nursing</institutionName>
      <specialization>nursing</specialization>
      <levelId>8</levelId>
      <indexNumber>DIPLOMA</indexNumber>
      <award/>
      <grade/>
      <startYear/>
      <endYear/>
    </institution>
  </accademicHistory>
  <employmentHistory>
    <employer>
      <employerName>muhimbili national hospital</employerName>
      <postalAddress>po box 65000</postalAddress>
      <physicalAddress>upanga dar es salaam</physicalAddress>
      <telephone>0222151599</telephone>
      <email>info@mnh.or.tz</email>
      <mobile/>
      <fax/>
      <startYear/>
      <endYear/>
      <extraInformation/>
    </employer>
  </employmentHistory>
  <financialSponsor>
    <sponsor>
      <sponsorName>scholastica charles luanda</sponsorName>
      <payerId>11</payerId>
      <postalAddress>65000</postalAddress>
      <physicalAddress>kimara dar es salaam</physicalAddress>
      <fax/>
      <sponsorfax>0786300033</sponsorfax>
      <mobile>0786300033</mobile>
      <email>sticascola@gmail.com</email>
      <financedItem/>
      <extraInformation/>
    </sponsor>
  </financialSponsor>
  <nextOfKins>
    <nextOfKin>
      <kinName>colleta simbaulanga</kinName>
      <relationship>mother</relationship>
      <postalAddress>box 2038</postalAddress>
      <physicalAddress>kihonda morogoro</physicalAddress>
      <fax/>
      <telephone>0682523523</telephone>
      <mobile>0682523523</mobile>
      <email>sticascola@gmail.com</email>
      <extraInformation/>
    </nextOfKin>
  </nextOfKins>
  <banks><bank><accountName>CHARLES, SCHOLASTICA</accountName><bankAccount>0152327717200</bankAccount><bankName>CRDB</bankName><branchName></branchName></bank></banks>
  <subjects/>
  <results/>
<isaacompletechecksum>afb14b91f55df73ed368cce5b7205dee</isaacompletechecksum></student>
